minecraftVersions/__init__.py
minecraftVersions/utils.py
minecraftVersions-1.0.5.2.dist-info/LICENSE
minecraftVersions-1.0.5.2.dist-info/METADATA
minecraftVersions-1.0.5.2.dist-info/WHEEL
minecraftVersions-1.0.5.2.dist-info/top_level.txt
minecraftVersions-1.0.5.2.dist-info/RECORD
