Metadata-Version: 2.1
Name: minecraftVersions
Version: 1.0.5.2
Summary: A simple Minecraft version wrapper written in Python
Home-page: https://github.com/tungdo0602/MinecraftVersions.py
Author: tungdo0602
License: MIT
Project-URL: Issue tracker, https://github.com/tungdo0602/MinecraftVersions.py/issues
Classifier: Development Status :: 5 - Production/Stable
Classifier: License :: OSI Approved :: MIT License
Classifier: Intended Audience :: Developers
Classifier: Natural Language :: English
Classifier: Operating System :: OS Independent
Classifier: Programming Language :: Python :: 3.8
Classifier: Programming Language :: Python :: 3.9
Classifier: Programming Language :: Python :: 3.10
Classifier: Topic :: Internet
Classifier: Topic :: Software Development :: Libraries
Classifier: Topic :: Software Development :: Libraries :: Python Modules
Classifier: Topic :: Utilities
Classifier: Typing :: Typed
Requires-Python: >=3.8.0
License-File: LICENSE
Requires-Dist: requests
